{
  "symbols": [
    {
      "keywords": [
        "뱀이",
        "뱀을",
        "구렁이",
        "독사",
        "실뱀",
        "백사",
        "큰 뱀",
        "뱀 한 마리"
      ],
      "score": 2,
      "category": "동물",
      "description": "지혜, 재물, 강렬한 에너지, 태몽",
      "advice": "재물운이 상승하거나 중요한 기회가 찾아올 징조입니다. 태몽일 가능성도 있습니다. 백사는 매우 귀한 길몽입니다."
    },
    {
      "keywords": [
        "돈을",
        "돈이",
        "많은 돈",
        "지폐",
        "동전",
        "금전",
        "보석",
        "다이아몬드",
        "황금",
        "수표",
        "돈다발",
        "금괴"
      ],
      "score": 5,
      "category": "재물",
      "description": "경제적 이득, 성취, 행운",
      "advice": "예상치 못한 재물이 들어오거나 노력의 결실을 맺을 수 있습니다. 동전보다는 지폐나 금덩어리가 더 좋습니다."
    },
    {
      "keywords": [
        "화재",
        "불길",
        "산불",
        "모닥불",
        "불이",
        "불을",
        "불타는",
        "큰 불"
      ],
      "score": 4,
      "category": "자연",
      "description": "번창, 열정, 소멸과 재생",
      "advice": "사업이나 학업이 크게 번창할 길몽입니다. 불길이 거세게 타오를수록 운세가 강합니다."
    },
    {
      "keywords": [
        "바다",
        "강물",
        "홍수",
        "빗물",
        "호수",
        "우물",
        "맑은 물",
        "큰 물",
        "파도",
        "물에",
        "물을",
        "수영장"
      ],
      "score": 1,
      "category": "자연",
      "description": "감정의 흐름, 세력, 정화",
      "advice": "맑은 물은 재물과 명예를, 탁한 물이나 홍수는 건강 문제나 구설수를 의미할 수 있습니다."
    },
    {
      "keywords": [
        "이빨",
        "치아",
        "앞니",
        "어금니",
        "사랑니",
        "틀니",
        "이가"
      ],
      "score": -2,
      "category": "신체",
      "description": "가족, 건강, 변화",
      "advice": "이가 빠지는 꿈은 주변 사람의 변동이나 건강 문제를 암시할 수 있습니다. 앓던 이가 빠지면 근심 해소입니다."
    },
    {
      "keywords": [
        "똥을",
        "소변",
        "오줌",
        "변기",
        "황금똥",
        "똥이",
        "배설물",
        "대변"
      ],
      "score": 5,
      "category": "신체",
      "description": "재물, 해소, 성과, 시원함",
      "advice": "전통적인 횡재수입니다. 똥을 만지거나 뒤집어쓰면 큰 재물이 들어옵니다. 오줌이 세차게 나오면 소원이 성취됩니다."
    },
    {
      "keywords": [
        "피가",
        "출혈",
        "생리",
        "코피",
        "선혈",
        "피를",
        "피 흘리는"
      ],
      "score": 3,
      "category": "신체",
      "description": "생명력, 재물, 진리, 순환",
      "advice": "몸에서 피가 나는 것은 재물 손실이 아니라 오히려 재물이 들어오거나 정신적 감화를 받는 길몽입니다."
    },
    {
      "keywords": [
        "조상",
        "할아버지",
        "할머니",
        "부모님",
        "돌아가신",
        "제사",
        "조상님"
      ],
      "score": 2,
      "category": "인물",
      "description": "보호, 경고, 메시지",
      "advice": "조상님의 표정이 밝으면 좋은 일이, 어두우면 사고나 문제를 조심하라는 경고입니다."
    },
    {
      "keywords": [
        "강아지",
        "애완견",
        "반려견",
        "멍멍이",
        "개 짖는",
        "개한테",
        "큰 개",
        "흰 개",
        "검은 개",
        "개에게 물리는",
        "갈색 강아지"
      ],
      "score": 0,
      "category": "동물",
      "description": "충성, 친구, 구설수, 다툼",
      "advice": "개를 쓰다듬으면 아랫사람으로 인한 속썩임이, 개가 짖거나 물면 구설수나 싸움이 생길 수 있습니다. 갈색 강아지는 신뢰를 의미합니다."
    },
    {
      "keywords": [
        "고양이",
        "야옹이",
        "고양이가",
        "고양이를",
        "검은 고양이",
        "흰 고양이"
      ],
      "score": 0,
      "category": "동물",
      "description": "비밀, 독립심, 까다로운 관계, 도둑",
      "advice": "숨겨진 재능을 발견할 수 있으나, 사기나 도난을 주의해야 할 수도 있습니다. 고양이가 다가오면 새로운 인연이 생길 수 있습니다."
    },
    {
      "keywords": [
        "호랑이",
        "사자",
        "맹수",
        "표범",
        "호랑이가",
        "호랑이를",
        "백호"
      ],
      "score": 4,
      "category": "동물",
      "description": "권력, 명예, 성공, 귀인",
      "advice": "큰 일을 성취하거나 높은 자리에 오를 수 있는 대길몽입니다. 태몽이라면 큰 인물이 태어납니다."
    },
    {
      "keywords": [
        "용이",
        "용을",
        "청룡",
        "황룡",
        "승천",
        "용 한 마리",
        "용을 타고"
      ],
      "score": 10,
      "category": "동물",
      "description": "최고의 권위, 부귀영화, 입신양명",
      "advice": "최고의 길몽 중 하나로, 명예와 부를 동시에 얻고 크게 성공할 징조입니다."
    },
    {
      "keywords": [
        "돼지가",
        "돼지를",
        "멧돼지",
        "흑돼지",
        "아기돼지",
        "돼지떼",
        "복돼지"
      ],
      "score": 5,
      "category": "동물",
      "description": "재물, 풍요, 복, 횡재",
      "advice": "로또 당첨 등 뜻밖의 큰 재물이 들어올 수 있는 길몽입니다. 돼지를 잡거나 집으로 데려오면 더욱 좋습니다."
    },
    {
      "keywords": [
        "날다",
        "비행",
        "하늘을",
        "공중부양",
        "날아",
        "날아가는"
      ],
      "score": 3,
      "category": "행동",
      "description": "상승, 자유, 과시, 소원성취",
      "advice": "신분이 상승하거나 답답했던 일이 해결되어 자유로워질 징조입니다. 새처럼 자유롭게 날면 목표를 달성합니다."
    },
    {
      "keywords": [
        "떨어지다",
        "추락",
        "낭떠러지",
        "절벽에서",
        "떨어지는"
      ],
      "score": -3,
      "category": "행동",
      "description": "실패, 좌절, 불안, 하락",
      "advice": "추진하던 일이 난관에 부딪히거나 자신감이 하락할 수 있습니다. 키 크는 꿈일 수도 있습니다(성장기)."
    },
    {
      "keywords": [
        "죽는",
        "장례식",
        "관을",
        "관이",
        "장례",
        "시신",
        "송장",
        "사망",
        "장례식 관",
        "영정사진"
      ],
      "score": 3,
      "category": "사건",
      "description": "재생, 새로운 시작, 해결, 유산",
      "advice": "현재의 고민이 해결되고 새로운 인생이 시작됩니다. 시체는 재물을 상징하기도 합니다."
    },
    {
      "keywords": [
        "시험",
        "면접",
        "불합격",
        "수능",
        "시험장"
      ],
      "score": -1,
      "category": "사건",
      "description": "평가, 불안, 압박, 실수",
      "advice": "실수하지 않을까 하는 심리적 불안이 반영된 경우가 많습니다. 준비를 철저히 하세요."
    },
    {
      "keywords": [
        "합격",
        "수석",
        "통과",
        "당선"
      ],
      "score": 5,
      "category": "사건",
      "description": "성취, 명예, 기쁨",
      "advice": "노력의 결실을 맺고 인정을 받습니다. 좋은 소식이 기다리고 있습니다."
    },
    {
      "keywords": [
        "운동화",
        "신발을",
        "슬리퍼",
        "맨발",
        "신을",
        "구두"
      ],
      "score": 1,
      "category": "물건",
      "description": "의지할 곳, 협조자, 이동, 지위",
      "advice": "새 신을 신으면 귀인을 만나거나 승진합니다. 신발을 잃어버리면 협조자를 잃거나 지위를 상실합니다."
    },
    {
      "keywords": [
        "새 옷",
        "옷이",
        "드레스",
        "정장",
        "의복",
        "헌 옷",
        "옷을",
        "한복"
      ],
      "score": 1,
      "category": "물건",
      "description": "신분, 명예, 보호, 과시",
      "advice": "새 옷이나 화려한 옷을 입으면 신분이 상승하고 좋은 소식을 듣습니다. 옷이 더러워지면 명예가 실추됩니다."
    },
    {
      "keywords": [
        "우리 집",
        "집을",
        "방에",
        "이사",
        "작은 방",
        "집으로",
        "큰 방",
        "집에",
        "큰 집",
        "아파트",
        "내 집",
        "새 집",
        "빈 집",
        "방을",
        "안방",
        "헌 집",
        "건물"
      ],
      "score": 1,
      "category": "장소",
      "description": "자신, 사업체, 안정, 기반",
      "advice": "집을 짓거나 넓은 집으로 이사가면 사업이 튼튼해지고 운세가 트입니다. 집이 무너지면 난관이 예상됩니다."
    },
    {
      "keywords": [
        "자동차",
        "승용차",
        "트럭",
        "운전",
        "버스",
        "기차",
        "택시",
        "차를",
        "차 타고"
      ],
      "score": 1,
      "category": "물건",
      "description": "사업 진행, 과시, 이동, 단체",
      "advice": "운전이 순조로우면 일이 잘 풀리지만, 차가 고장나거나 사고가 나면 방해물이 생깁니다."
    },
    {
      "keywords": [
        "머리카락",
        "미용실",
        "이발",
        "염색",
        "대머리",
        "머리를",
        "머리카락이"
      ],
      "score": 0,
      "category": "신체",
      "description": "근심, 자존심, 협조, 수명",
      "advice": "머리를 자르는 것은 근심 해소를 의미할 수도, 자존심 상실을 의미할 수도 있습니다. 윤기나는 머리는 건강을 상징합니다."
    },
    {
      "keywords": [
        "벌레",
        "곤충",
        "바퀴벌레",
        "지렁이",
        "벌레가",
        "벌레를"
      ],
      "score": -1,
      "category": "동물",
      "description": "귀찮은 일, 소소한 이득, 방해꾼",
      "advice": "사소한 일로 신경 쓸 일이 생기거나 건강에 유의해야 합니다. 벌레를 죽이면 고민이 해결됩니다."
    },
    {
      "keywords": [
        "함박눈",
        "설원",
        "눈보라",
        "눈송이",
        "눈사람",
        "눈이 내리는",
        "쌓인 눈"
      ],
      "score": 2,
      "category": "자연",
      "description": "순수, 정화, 고립, 재산",
      "advice": "함박눈은 풍요와 평화를 상징하지만, 눈보라는 고난을 의미합니다. 눈을 치우면 방해물을 제거하는 것입니다."
    },
    {
      "keywords": [
        "전신거울",
        "거울을"
      ],
      "score": 0,
      "category": "물건",
      "description": "자아성찰, 소식, 배우자, 마음",
      "advice": "거울을 보며 만족하면 길몽, 깨지거나 흐리면 흉몽입니다. 반가운 사람을 만날 수도 있습니다."
    },
    {
      "keywords": [
        "칼을",
        "송곳",
        "검",
        "칼에",
        "칼로",
        "도검",
        "식칼",
        "검을",
        "가위",
        "장검"
      ],
      "score": 1,
      "category": "물건",
      "description": "권위, 해결, 공격성, 끊음",
      "advice": "경쟁자를 물리치거나 권위를 얻게 됩니다. 다치거나 남을 해치는 것은 해결과 성취를 의미합니다."
    },
    {
      "keywords": [
        "가위눌림",
        "가위 눌리",
        "몸이 안 움직"
      ],
      "score": -2,
      "category": "신체",
      "description": "심리적 압박, 건강 이상, 스트레스",
      "advice": "현재 심리적으로 매우 불안하거나 건강이 좋지 않을 수 있습니다. 휴식이 필요합니다."
    },
    {
      "keywords": [
        "아기",
        "아이",
        "임신",
        "출산",
        "쌍둥이",
        "아기를",
        "갓난아기"
      ],
      "score": -1,
      "category": "인물",
      "description": "책임, 근심, 새로운 일, 성과",
      "advice": "아기를 안고 있으면 근심거리가 생기지만, 아기를 낳는 꿈은 새로운 성과나 권리를 얻는 길몽입니다."
    },
    {
      "keywords": [
        "연예인",
        "유명인",
        "가수",
        "배우",
        "아이돌",
        "스타"
      ],
      "score": 2,
      "category": "인물",
      "description": "동경, 명예욕, 소식, 귀인",
      "advice": "유명인과 만나거나 데이트하면 좋은 소식을 듣거나 자신의 이름을 알릴 기회가 생깁니다."
    },
    {
      "keywords": [
        "화장실",
        "소변기",
        "변기통"
      ],
      "score": 2,
      "category": "장소",
      "description": "해소, 처리, 사생활, 재물",
      "advice": "화장실에서 볼일을 시원하게 보면 고민이 해결되고 재물이 들어옵니다. 화장실을 못 찾아 헤매면 일이 꼬입니다."
    },
    {
      "keywords": [
        "산에",
        "언덕",
        "높은 산",
        "산을",
        "절벽",
        "산속",
        "정상",
        "등산"
      ],
      "score": 3,
      "category": "자연",
      "description": "목표, 성취, 난관, 희망",
      "advice": "정상에 올랐다면 소원을 성취하고 명예를 얻습니다. 산을 내려오거나 길을 잃으면 하락세일 수 있습니다."
    },
    {
      "keywords": [
        "물고기",
        "낚시",
        "생선회",
        "그물",
        "물고기를",
        "월척"
      ],
      "score": 3,
      "category": "동물",
      "description": "재물, 성취, 활력, 기회",
      "advice": "싱싱한 물고기를 잡으면 재물을 얻거나 좋은 사람을 만납니다. 놓치면 기회를 잃습니다."
    },
    {
      "keywords": [
        "까치",
        "까마귀",
        "독수리",
        "참새",
        "비둘기",
        "새떼",
        "앵무새",
        "새가",
        "작은 새"
      ],
      "score": 2,
      "category": "동물",
      "description": "소식, 자유, 명예, 권력",
      "advice": "예쁜 새나 까치는 좋은 소식을, 까마귀는 흉한 소식을 의미할 수 있습니다. 독수리는 권력을 상징합니다."
    },
    {
      "keywords": [
        "승마",
        "백마",
        "말타",
        "조랑말",
        "말을",
        "말이 달리는",
        "말 타는"
      ],
      "score": 3,
      "category": "동물",
      "description": "추진력, 이동, 성공, 에너지",
      "advice": "말을 타고 달리면 일이 일사천리로 진행됩니다. 말에서 떨어지면 실패를 주의하세요."
    },
    {
      "keywords": [
        "황소",
        "암소",
        "송아지",
        "음메",
        "소가",
        "소를",
        "소떼"
      ],
      "score": 4,
      "category": "동물",
      "description": "조상, 재산, 성실, 집안",
      "advice": "조상이 돕거나 재산이 불어날 징조입니다. 소가 집으로 들어오면 가문이 번창합니다."
    },
    {
      "keywords": [
        "생쥐",
        "흰쥐",
        "쥐가",
        "쥐를",
        "쥐떼"
      ],
      "score": -1,
      "category": "동물",
      "description": "근심, 도둑, 숨겨진 일, 부하",
      "advice": "사소한 일로 신경 쓰이거나 물건을 잃어버릴 수 있습니다. 쥐를 잡으면 범인을 잡거나 문제를 해결합니다."
    },
    {
      "keywords": [
        "거북이",
        "자라",
        "거북이를"
      ],
      "score": 5,
      "category": "동물",
      "description": "장수, 재물, 높은 지위, 도움",
      "advice": "뜻밖의 횡재를 하거나 건강이 좋아집니다. 거북이를 타거나 만지면 부귀영화를 누립니다."
    },
    {
      "keywords": [
        "천둥",
        "번개",
        "벼락"
      ],
      "score": 3,
      "category": "자연",
      "description": "명성, 충격, 변화, 깨달음",
      "advice": "세상이 놀랄만한 일을 해내거나 큰 소식을 듣습니다. 벼락을 맞으면 대박이 날 징조입니다."
    },
    {
      "keywords": [
        "태양",
        "일출",
        "햇빛",
        "해돋이",
        "해가",
        "해를"
      ],
      "score": 5,
      "category": "자연",
      "description": "절대적 권력, 진리, 영광, 시작",
      "advice": "사업이나 소원이 크게 이루어질 대길몽입니다. 해를 품거나 삼키면 태몽으로 위인을 낳습니다."
    },
    {
      "keywords": [
        "보름달",
        "초승달",
        "달빛",
        "달이"
      ],
      "score": 3,
      "category": "자연",
      "description": "풍요, 여성, 감수성, 결실",
      "advice": "태몽이거나 예술적인 성취를 이룰 수 있습니다. 달빛이 집안을 비추면 경사가 생깁니다."
    },
    {
      "keywords": [
        "은하수",
        "유성",
        "별똥별",
        "북두칠성",
        "샛별",
        "별이",
        "별을",
        "밤하늘 별"
      ],
      "score": 4,
      "category": "자연",
      "description": "희망, 인기, 영감, 지도자",
      "advice": "스타가 되거나 소원을 이룰 징조입니다. 별이 떨어지면 유명인의 죽음이나 하락을 의미할 수 있습니다."
    },
    {
      "keywords": [
        "꽃이",
        "꽃을",
        "꽃다발",
        "나무",
        "장미",
        "국화",
        "예쁜 꽃",
        "꽃밭"
      ],
      "score": 2,
      "category": "자연",
      "description": "사랑, 영광, 결실, 아름다움",
      "advice": "아름다운 꽃을 보면 연애운이 상승하거나 상을 받습니다. 나무에 열매가 열리면 성과를 얻습니다."
    },
    {
      "keywords": [
        "눈동자",
        "눈알",
        "시력",
        "눈이 안보"
      ],
      "score": 1,
      "category": "신체",
      "description": "통찰력, 판단, 마음의 창",
      "advice": "눈이 밝아지면 지혜를 얻고, 눈병이 나거나 멀면 판단력이 흐려져 사기를 당할 수 있습니다."
    },
    {
      "keywords": [
        "왼손",
        "내 팔",
        "오른손",
        "손 잡는",
        "팔이",
        "손이",
        "팔을",
        "손가락",
        "손을",
        "악수",
        "내 손",
        "팔뚝"
      ],
      "score": 1,
      "category": "신체",
      "description": "권력, 도움, 일, 형제",
      "advice": "손을 잡으면 협력자를 만나고, 손을 다치면 세력을 잃거나 형제에게 우환이 생깁니다."
    },
    {
      "keywords": [
        "나체",
        "벌거벗은",
        "알몸",
        "목욕탕"
      ],
      "score": -2,
      "category": "신체",
      "description": "수치심, 공개, 진실, 무방비",
      "advice": "부끄러웠다면 비밀이 탄로나 곤란해질 수 있습니다. 당당했다면 자신의 모든 것을 보여주고 인정받습니다."
    },
    {
      "keywords": [
        "친구",
        "동창",
        "동료",
        "친구가"
      ],
      "score": 1,
      "category": "인물",
      "description": "대인관계, 또 다른 자아, 협력",
      "advice": "친구와 사이좋게 지내면 실제 관계도 좋아집니다. 친구가 울면 그 친구에게 안 좋은 일이 생길 수 있습니다."
    },
    {
      "keywords": [
        "도둑",
        "강도",
        "괴한",
        "도둑이"
      ],
      "score": -2,
      "category": "인물",
      "description": "상실, 불안, 해결, 기회",
      "advice": "도둑이 들어 물건이 없어지면 오히려 근심이 사라질 수도 있습니다. 도둑을 잡으면 잃었던 것을 되찾습니다."
    },
    {
      "keywords": [
        "반지를",
        "목걸이",
        "금반지",
        "귀걸이",
        "보석"
      ],
      "score": 3,
      "category": "물건",
      "description": "약속, 결혼, 권리, 명예",
      "advice": "미혼자는 결혼운이, 기혼자는 계약 성사가 예상됩니다. 반지를 잃어버리면 이별수가 있습니다."
    },
    {
      "keywords": [
        "무덤",
        "산소",
        "비석"
      ],
      "score": 2,
      "category": "장소",
      "description": "기관, 집, 비밀, 과거",
      "advice": "무덤을 보면 협조 기관의 도움을 받거나 비밀을 간직합니다. 무덤에서 빛이 나면 명예를 얻습니다."
    },
    {
      "keywords": [
        "전화",
        "스마트폰",
        "핸드폰",
        "통화"
      ],
      "score": 0,
      "category": "물건",
      "description": "소식, 중개, 수다, 정보",
      "advice": "긴 통화는 일의 진행을, 불통은 답답함을 의미합니다. 전화벨 소리는 새로운 소식을 알립니다."
    },
    {
      "keywords": [
        "먹다",
        "음식",
        "식사",
        "잔치",
        "먹는",
        "맛있는"
      ],
      "score": 1,
      "category": "행동",
      "description": "습득, 욕구, 질병, 일거리",
      "advice": "맛있게 먹으면 일을 성취하지만, 억지로 먹거나 상한 음식을 먹으면 병이 날 수 있습니다."
    },
    {
      "keywords": [
        "결혼",
        "웨딩드레스",
        "청혼",
        "결혼식"
      ],
      "score": 1,
      "category": "사건",
      "description": "계약, 결합, 변화, 새로운 시작",
      "advice": "새로운 일을 시작하거나 계약을 맺게 됩니다. 실제 결혼보다는 일적인 결합을 의미하는 경우가 많습니다."
    },
    {
      "keywords": [
        "길을 잃다",
        "미로",
        "방황",
        "길 잃은"
      ],
      "score": -3,
      "category": "행동",
      "description": "방황, 불안, 중단, 고립",
      "advice": "목표를 잃고 헤매거나 일이 중단될 수 있습니다. 조력자를 찾아야 합니다."
    },
    {
      "keywords": [
        "목욕",
        "샤워",
        "세수",
        "온천"
      ],
      "score": 2,
      "category": "행동",
      "description": "정화, 해소, 새로운 출발",
      "advice": "묵은 때를 씻어내듯 근심 걱정이 사라지고 건강이 좋아질 길몽입니다."
    },
    {
      "keywords": [
        "꿀벌",
        "벌에 쏘이는",
        "벌이",
        "말벌",
        "벌떼"
      ],
      "score": 0,
      "category": "동물",
      "description": "성실, 재물, 공격, 두려움",
      "advice": "벌이 꿀을 모으면 재물이 늘어나지만, 벌에 쏘이면 질병이나 다툼이 생길 수 있습니다."
    },
    {
      "keywords": [
        "개미",
        "개미떼",
        "개미가"
      ],
      "score": 1,
      "category": "동물",
      "description": "성실, 협동, 노력, 스트레스",
      "advice": "꾸준히 노력하면 성과를 얻습니다. 개미 떼가 우글거리면 스트레스를 받을 수 있습니다."
    },
    {
      "keywords": [
        "귀신이",
        "악령",
        "악마",
        "도깨비",
        "유령"
      ],
      "score": -2,
      "category": "인물",
      "description": "불안, 스트레스, 병, 방해",
      "advice": "심리적인 불안감이 크거나 건강에 이상이 생길 수 있습니다. 귀신을 물리치면 문제를 해결합니다."
    },
    {
      "keywords": [
        "토끼",
        "산토끼",
        "토끼가",
        "토끼를"
      ],
      "score": 2,
      "category": "동물",
      "description": "행운, 번식, 재물, 소심함",
      "advice": "뜻밖의 행운이 찾아오거나 재물이 늘어날 징조입니다. 토끼를 잡으면 더욱 좋습니다."
    },
    {
      "keywords": [
        "원숭이",
        "원숭이가"
      ],
      "score": -1,
      "category": "동물",
      "description": "재주, 잔꾀, 구설수, 모방",
      "advice": "지나친 욕심이나 잔꾀로 인해 오히려 화를 입을 수 있습니다. 말조심하세요."
    },
    {
      "keywords": [
        "닭을",
        "암탉",
        "수탉",
        "통닭",
        "닭이",
        "닭 우는"
      ],
      "score": 1,
      "category": "동물",
      "description": "새로운 시작, 알림, 관직, 명성",
      "advice": "새벽을 알리는 닭처럼 새로운 일이 시작되거나 좋은 소식을 듣게 됩니다. 닭이 알을 낳으면 재물이 생깁니다."
    },
    {
      "keywords": [
        "염소",
        "양떼",
        "흰 양",
        "양 한 마리",
        "새끼 양"
      ],
      "score": 2,
      "category": "동물",
      "description": "평화, 재물, 교육, 자비",
      "advice": "마음이 평안해지고 재물이 들어옵니다. 교육자나 성직자에게 좋은 꿈입니다."
    },
    {
      "keywords": [
        "곰",
        "반달곰",
        "곰이",
        "곰을"
      ],
      "score": 3,
      "category": "동물",
      "description": "권력, 인내, 큰 재물, 뚝심",
      "advice": "끈기 있게 노력하면 큰 성과를 거두고 부귀영화를 누립니다. 태몽일 수 있습니다."
    },
    {
      "keywords": [
        "코끼리",
        "코끼리가"
      ],
      "score": 4,
      "category": "동물",
      "description": "큰 덕, 부귀, 장수, 든든한 후원자",
      "advice": "매우 귀한 길몽으로, 든든한 후원자를 만나거나 큰 부를 얻게 됩니다."
    },
    {
      "keywords": [
        "돌고래",
        "고래",
        "고래가"
      ],
      "score": 3,
      "category": "동물",
      "description": "행운, 가족, 협력, 귀인",
      "advice": "가족애가 깊어지고 귀인의 도움을 받아 일이 술술 풀립니다."
    },
    {
      "keywords": [
        "상어",
        "상어가"
      ],
      "score": -2,
      "category": "동물",
      "description": "위험, 공격, 권력, 경쟁자",
      "advice": "강력한 경쟁자나 위험 인물이 나타날 수 있으니 주의가 필요합니다."
    },
    {
      "keywords": [
        "비가",
        "비를",
        "폭우",
        "빗줄기",
        "장마",
        "비오는",
        "내리는 비"
      ],
      "score": 1,
      "category": "자연",
      "description": "정화, 풍요, 시련, 감정",
      "advice": "촉촉한 비는 축복과 풍요를, 폭우는 시련을 의미하지만 비 온 뒤 땅이 굳어집니다."
    },
    {
      "keywords": [
        "무지개",
        "쌍무지개"
      ],
      "score": 5,
      "category": "자연",
      "description": "희망, 경사, 결혼, 명예",
      "advice": "최고의 길몽 중 하나로, 모든 일이 뜻대로 이루어지고 경사가 생깁니다."
    },
    {
      "keywords": [
        "구름",
        "먹구름",
        "흰구름",
        "구름이"
      ],
      "score": 0,
      "category": "자연",
      "description": "변화, 방해, 신비, 덧없음",
      "advice": "흰 구름은 길조이나, 먹구름은 근심이나 질병을 암시할 수 있습니다."
    },
    {
      "keywords": [
        "바람",
        "태풍",
        "폭풍",
        "강풍",
        "바람이"
      ],
      "score": -1,
      "category": "자연",
      "description": "변동, 시련, 권세, 이동",
      "advice": "주변 환경이 급변하거나 시련이 닥칠 수 있습니다. 잘 견뎌내면 기회가 됩니다."
    },
    {
      "keywords": [
        "과일",
        "열매",
        "수확"
      ],
      "score": 2,
      "category": "식물",
      "description": "결실, 태몽, 재물, 사랑",
      "advice": "노력의 결실을 맺습니다. 잘 익은 과일일수록 운세가 좋습니다."
    },
    {
      "keywords": [
        "사과",
        "사과를"
      ],
      "score": 2,
      "category": "식물",
      "description": "사랑, 결실, 유혹, 성공",
      "advice": "애정운이 좋아지거나 현재 진행 중인 일이 좋은 결과를 맺습니다."
    },
    {
      "keywords": [
        "복숭아",
        "복숭아를"
      ],
      "score": 3,
      "category": "식물",
      "description": "연애, 장수, 태몽, 매력",
      "advice": "매력이 넘쳐 인기가 많아지고, 연애운이 급상승합니다. 예쁜 딸 태몽입니다."
    },
    {
      "keywords": [
        "포도",
        "포도를"
      ],
      "score": 2,
      "category": "식물",
      "description": "다산, 수확, 이익, 생활",
      "advice": "주렁주렁 열린 포도처럼 재물이나 성과가 연이어 들어옵니다."
    },
    {
      "keywords": [
        "고구마",
        "고구마를"
      ],
      "score": 2,
      "category": "식물",
      "description": "재물, 풍요, 태몽",
      "advice": "경제적 안정을 의미하며, 태몽일 경우 건강한 아들을 상징합니다."
    },
    {
      "keywords": [
        "고기",
        "고기를",
        "삼겹살",
        "갈비"
      ],
      "score": 2,
      "category": "음식",
      "description": "즐거움, 에너지, 자원",
      "advice": "고기를 굽거나 먹는 것은 일상의 즐거움이나 에너지를 얻는 것을 의미합니다."
    },
    {
      "keywords": [
        "고름",
        "고름 짜는"
      ],
      "score": 1,
      "category": "신체",
      "description": "해소, 치유, 해결",
      "advice": "아픈 곳이 낫거나 골치 아픈 문제가 해결될 징조입니다."
    },
    {
      "keywords": [
        "거미",
        "거미줄",
        "거미가"
      ],
      "score": 0,
      "category": "동물",
      "description": "창의성, 인내, 함정, 불안",
      "advice": "거미줄에 걸리면 곤란한 일에 휘말리지만, 거미가 집을 짓는 것을 보면 경사가 생깁니다."
    },
    {
      "keywords": [
        "키를",
        "키가",
        "열쇠"
      ],
      "score": 3,
      "category": "물건",
      "description": "해결, 권한, 합격, 비밀",
      "advice": "문제의 해결책을 찾거나 주도권을 쥐게 됩니다. 합격이나 승진의 징조입니다."
    },
    {
      "keywords": [
        "배낭",
        "가방을",
        "핸드백"
      ],
      "score": 1,
      "category": "물건",
      "description": "협조자, 신분, 짐, 재산",
      "advice": "무거운 가방은 근심거리지만, 새 가방을 사거나 받으면 신분이 상승합니다."
    },
    {
      "keywords": [
        "모자를",
        "헬멧"
      ],
      "score": 1,
      "category": "물건",
      "description": "명예, 보호, 신분, 직업",
      "advice": "새 모자를 쓰면 취직하거나 승진하여 명예를 얻습니다."
    },
    {
      "keywords": [
        "우산을",
        "양산"
      ],
      "score": 1,
      "category": "물건",
      "description": "보호, 방어, 협조자, 예방",
      "advice": "어려움 속에서 보호막이 생기거나 도와줄 사람이 나타납니다."
    },
    {
      "keywords": [
        "침대",
        "침대에"
      ],
      "score": 0,
      "category": "물건",
      "description": "휴식, 결혼, 병상, 사업 기반",
      "advice": "새 침대는 결혼이나 새 사업을, 침대 다리가 부러지면 사업상 어려움을 뜻합니다."
    },
    {
      "keywords": [
        "학교",
        "교실",
        "운동장",
        "학교에서"
      ],
      "score": 0,
      "category": "장소",
      "description": "규칙, 배움, 과거 회상, 압박",
      "advice": "현재의 심리적 압박이나 새로운 배움의 필요성을 나타냅니다."
    },
    {
      "keywords": [
        "병원",
        "의사",
        "간호사",
        "수술"
      ],
      "score": -1,
      "category": "장소",
      "description": "치유, 검진, 휴식, 불안",
      "advice": "건강에 대한 염려나 실제 검진이 필요함을 암시합니다. 치료받으면 호전됩니다."
    },
    {
      "keywords": [
        "경찰",
        "형사",
        "파출소",
        "경찰관"
      ],
      "score": -2,
      "category": "인물",
      "description": "규제, 양심, 압박, 사고",
      "advice": "법적인 문제나 양심의 가책을 느낄 일이 생길 수 있습니다. 행동을 조심하세요."
    },
    {
      "keywords": [
        "대통령",
        "임금",
        "왕",
        "황제"
      ],
      "score": 5,
      "category": "인물",
      "description": "최고 권력, 명예, 귀인, 은혜",
      "advice": "최고의 길몽으로, 강력한 후원자를 만나거나 큰 명예를 얻습니다."
    },
    {
      "keywords": [
        "수영",
        "헤엄",
        "수영하는"
      ],
      "score": 2,
      "category": "행동",
      "description": "활동, 경쟁, 성취, 만족",
      "advice": "넓은 물에서 마음껏 수영하면 소원을 성취하고 사업이 번창합니다."
    },
    {
      "keywords": [
        "지네",
        "지네가"
      ],
      "score": 1,
      "category": "동물",
      "description": "재물, 끈기, 회복",
      "advice": "징그러워 보이지만 지네는 재물을 상징합니다. 건강이 회복될 수도 있습니다."
    },
    {
      "keywords": [
        "구더기",
        "구더기가"
      ],
      "score": 2,
      "category": "동물",
      "description": "더러움 속의 재물, 횡재",
      "advice": "구더기가 득실거리면 재물이 크게 불어날 길몽입니다."
    },
    {
      "keywords": [
        "파리",
        "파리떼"
      ],
      "score": -1,
      "category": "동물",
      "description": "방해꾼, 근심, 질병",
      "advice": "귀찮은 일이나 사람이 꼬일 수 있습니다. 파리를 잡으면 해결됩니다."
    },
    {
      "keywords": [
        "모기",
        "모기가"
      ],
      "score": -1,
      "category": "동물",
      "description": "침입자, 소모, 방해",
      "advice": "자신의 재산이나 노력을 빼앗으려는 사람이 있을 수 있습니다."
    },
    {
      "keywords": [
        "떡이",
        "떡을",
        "송편",
        "시루떡",
        "가래떡"
      ],
      "score": 2,
      "category": "음식",
      "description": "재물, 일거리, 지식",
      "advice": "떡을 먹거나 받으면 재물이 들어오거나 일거리를 얻게 됩니다."
    },
    {
      "keywords": [
        "술을",
        "음주",
        "양주",
        "맥주",
        "술자리",
        "술 마시는",
        "소주"
      ],
      "score": 0,
      "category": "음식",
      "description": "대인관계, 실수, 망각, 영감",
      "advice": "적당히 마시면 대인관계가 좋아지지만, 취하면 실수나 구설수에 오를 수 있습니다."
    },
    {
      "keywords": [
        "쌀밥",
        "식사",
        "밥이",
        "밥을",
        "쌀"
      ],
      "score": 2,
      "category": "음식",
      "description": "재산, 건강, 평안",
      "advice": "쌀이 가득하면 부자가 되고, 따뜻한 밥을 먹으면 건강하고 평안해집니다."
    },
    {
      "keywords": [
        "손목시계",
        "시계를"
      ],
      "score": 1,
      "category": "물건",
      "description": "시간, 약속, 수명, 동업자",
      "advice": "새 시계를 사면 좋은 동업자를 만나거나 새로운 일을 계획하게 됩니다."
    },
    {
      "keywords": [
        "달리기",
        "마라톤",
        "뛰는"
      ],
      "score": 1,
      "category": "행동",
      "description": "노력, 과정, 급박함",
      "advice": "목표를 향해 열심히 노력하는 상태입니다. 1등으로 들어오면 소원 성취입니다."
    },
    {
      "keywords": [
        "화장",
        "메이크업"
      ],
      "score": 1,
      "category": "행동",
      "description": "변신, 위장, 명예, 과시",
      "advice": "자신을 돋보이게 하여 명예를 얻거나, 반대로 본심을 숨기는 것을 의미합니다."
    },
    {
      "keywords": [
        "감옥",
        "교도소",
        "수갑"
      ],
      "score": -2,
      "category": "장소",
      "description": "억압, 통제, 복종, 자산관리",
      "advice": "자신의 뜻대로 일이 풀리지 않거나 심리적 압박을 받을 수 있습니다."
    },
    {
      "keywords": [
        "군인",
        "장군",
        "군대",
        "군 복무"
      ],
      "score": 1,
      "category": "인물",
      "description": "규율, 힘, 난관 극복, 책임",
      "advice": "어려움을 극복하고 목표를 달성할 힘을 얻습니다. 장군을 만나면 귀인의 도움을 받습니다."
    },
    {
      "keywords": [
        "부처님",
        "사찰",
        "절에",
        "스님"
      ],
      "score": 3,
      "category": "장소",
      "description": "평화, 귀인, 소원성취, 진리",
      "advice": "마음의 평화를 얻고 귀인을 만나 도움을 받습니다. 부처님을 보면 대길몽입니다."
    },
    {
      "keywords": [
        "교회",
        "성당",
        "목사님",
        "신부님",
        "예수님"
      ],
      "score": 3,
      "category": "장소",
      "description": "진리, 구원, 지도자, 안식",
      "advice": "진리를 깨닫거나 훌륭한 지도자의 도움을 받아 문제를 해결합니다."
    },
    {
      "keywords": [
        "눈물",
        "울음",
        "우는"
      ],
      "score": 1,
      "category": "행동",
      "description": "해소, 기쁨, 감정 표현",
      "advice": "꿈에서 펑펑 울면 현실에서는 막혔던 일이 시원하게 풀리고 기쁜 일이 생깁니다."
    },
    {
      "keywords": [
        "안개",
        "자욱한",
        "흐릿한"
      ],
      "score": -1,
      "category": "자연",
      "description": "불확실, 미궁, 근심",
      "advice": "앞길이 막막하거나 일이 잘 풀리지 않을 수 있습니다. 때를 기다리세요."
    },
    {
      "keywords": [
        "지진",
        "땅이 흔들",
        "갈라지는"
      ],
      "score": -2,
      "category": "자연",
      "description": "변동, 불안, 파탄, 이동",
      "advice": "가정이나 직장에 큰 변화가 생길 징조입니다. 미리 대비하는 것이 좋습니다."
    },
    {
      "keywords": [
        "진흙",
        "수렁",
        "흙탕물"
      ],
      "score": -1,
      "category": "자연",
      "description": "곤란, 질병, 창피",
      "advice": "하는 일이 꼬이거나 건강에 문제가 생길 수 있습니다."
    },
    {
      "keywords": [
        "바위",
        "큰 돌",
        "암석"
      ],
      "score": 2,
      "category": "자연",
      "description": "재물, 기반, 굳건함",
      "advice": "재물이 들어오거나 튼튼한 기반을 다지게 됩니다. 바위를 안으면 횡재수입니다."
    },
    {
      "keywords": [
        "동굴",
        "터널",
        "지하"
      ],
      "score": 0,
      "category": "장소",
      "description": "비밀, 탐구, 피신, 발견",
      "advice": "깊은 연구를 하거나 비밀을 간직하게 됩니다. 동굴에서 나오면 밝은 미래가 기다립니다."
    },
    {
      "keywords": [
        "늑대",
        "늑대가",
        "늑대를"
      ],
      "score": -2,
      "category": "동물",
      "description": "도둑, 강도, 위험, 배신",
      "advice": "믿었던 사람에게 배신을 당하거나 물건을 잃어버릴 수 있습니다."
    },
    {
      "keywords": [
        "여우",
        "여우가"
      ],
      "score": -1,
      "category": "동물",
      "description": "교활, 유혹, 사기",
      "advice": "남의 꾐에 넘어가거나 의심받을 일이 생길 수 있습니다."
    },
    {
      "keywords": [
        "사슴",
        "꽃사슴"
      ],
      "score": 2,
      "category": "동물",
      "description": "명예, 온순, 귀인",
      "advice": "귀한 사람을 만나거나 명예를 얻습니다. 태몽일 경우 예쁜 딸을 낳습니다."
    },
    {
      "keywords": [
        "사자",
        "사자가",
        "사자를"
      ],
      "score": 4,
      "category": "동물",
      "description": "권위, 성공, 승리",
      "advice": "호랑이 꿈과 마찬가지로 크게 성공하고 명성을 떨칠 대길몽입니다."
    },
    {
      "keywords": [
        "봉황",
        "봉황새"
      ],
      "score": 5,
      "category": "동물",
      "description": "최고의 명예, 귀한 신분, 결혼",
      "advice": "부귀영화를 누리고 미혼자는 훌륭한 배우자를 만납니다."
    },
    {
      "keywords": [
        "박쥐",
        "박쥐가"
      ],
      "score": -1,
      "category": "동물",
      "description": "음흉, 비밀, 소식",
      "advice": "남 모르게 일을 처리하거나 좋지 않은 소식을 들을 수 있습니다."
    },
    {
      "keywords": [
        "오리",
        "청둥오리",
        "오리가"
      ],
      "score": 1,
      "category": "동물",
      "description": "평화, 인연, 즐거움",
      "advice": "좋은 인연을 만나거나 즐거운 일이 생깁니다."
    },
    {
      "keywords": [
        "백조",
        "고니"
      ],
      "score": 2,
      "category": "동물",
      "description": "우아함, 명성, 예술",
      "advice": "예술적 성취를 이루거나 명성을 얻습니다."
    },
    {
      "keywords": [
        "공작",
        "공작새"
      ],
      "score": 3,
      "category": "동물",
      "description": "화려함, 부귀, 명예",
      "advice": "화려한 날개를 펴면 부귀영화를 누리게 됩니다."
    },
    {
      "keywords": [
        "낙타",
        "낙타를"
      ],
      "score": 1,
      "category": "동물",
      "description": "인내, 자산, 이동",
      "advice": "오랜 노력 끝에 결실을 맺거나 자산이 늘어납니다."
    },
    {
      "keywords": [
        "악어",
        "악어가"
      ],
      "score": -1,
      "category": "동물",
      "description": "위험, 강압, 권력",
      "advice": "강력한 세력에게 압박을 받거나 위험에 처할 수 있습니다."
    },
    {
      "keywords": [
        "개구리",
        "두꺼비",
        "맹꽁이"
      ],
      "score": 1,
      "category": "동물",
      "description": "재물, 기회, 소식",
      "advice": "두꺼비는 재물을, 개구리는 새로운 기회나 소식을 의미합니다."
    },
    {
      "keywords": [
        "나무",
        "소나무",
        "대나무"
      ],
      "score": 2,
      "category": "식물",
      "description": "성장, 기반, 절개",
      "advice": "푸른 나무는 사업의 번창을, 죽은 나무는 실패를 의미합니다."
    },
    {
      "keywords": [
        "숲을",
        "숲속",
        "정글",
        "밀림"
      ],
      "score": 1,
      "category": "자연",
      "description": "풍요, 미지, 탐험",
      "advice": "새로운 분야에 도전하거나 풍요로운 자원을 얻습니다."
    },
    {
      "keywords": [
        "풀밭",
        "잔디",
        "잡초"
      ],
      "score": 1,
      "category": "식물",
      "description": "생명력, 번창, 기반",
      "advice": "잘 가꿔진 잔디밭은 평안과 안정을 의미합니다."
    },
    {
      "keywords": [
        "버섯",
        "송이버섯"
      ],
      "score": 1,
      "category": "식물",
      "description": "재물, 태몽, 영감",
      "advice": "뜻밖의 재물을 얻거나 귀한 아이를 가질 태몽입니다."
    },
    {
      "keywords": [
        "인삼",
        "산삼"
      ],
      "score": 5,
      "category": "식물",
      "description": "건강, 장수, 횡재",
      "advice": "건강이 좋아지고 큰 재물이 들어올 대길몽입니다."
    },
    {
      "keywords": [
        "빵이",
        "빵을",
        "케이크",
        "식빵",
        "샌드위치"
      ],
      "score": 1,
      "category": "음식",
      "description": "생활, 만족, 애정",
      "advice": "생활이 넉넉해지고 마음의 여유가 생깁니다."
    },
    {
      "keywords": [
        "국수",
        "라면",
        "짜장면"
      ],
      "score": 1,
      "category": "음식",
      "description": "장수, 인연, 결합",
      "advice": "긴 국수는 장수와 좋은 인연이 오래감을 상징합니다."
    },
    {
      "keywords": [
        "달걀",
        "알을",
        "새알",
        "계란"
      ],
      "score": 2,
      "category": "음식",
      "description": "시작, 가능성, 재물",
      "advice": "새로운 일을 시작하거나 재물을 얻습니다. 알을 깨면 새로운 세상이 열립니다."
    },
    {
      "keywords": [
        "우유",
        "두유"
      ],
      "score": 1,
      "category": "음식",
      "description": "영양, 정신적 자원, 교육",
      "advice": "지식을 습득하거나 정신적으로 성숙해집니다."
    },
    {
      "keywords": [
        "음료수",
        "마시는 차",
        "자동차",
        "승용차",
        "녹차",
        "커피",
        "홍차"
      ],
      "score": 0,
      "category": "음식",
      "description": "휴식, 대화, 자극",
      "advice": "사람들과 교류하거나 잠시 휴식을 취하게 됩니다."
    },
    {
      "keywords": [
        "기관총",
        "총을",
        "권총",
        "소총",
        "총기"
      ],
      "score": 2,
      "category": "물건",
      "description": "공격, 해결, 권력",
      "advice": "어려운 문제를 강력하게 해결하거나 권력을 쥐게 됩니다."
    },
    {
      "keywords": [
        "의자",
        "소파"
      ],
      "score": 1,
      "category": "물건",
      "description": "지위, 휴식, 안식처",
      "advice": "편안한 의자에 앉으면 지위가 오르거나 안정을 찾습니다."
    },
    {
      "keywords": [
        "책상",
        "테이블"
      ],
      "score": 1,
      "category": "물건",
      "description": "사업, 학업, 책임",
      "advice": "책상을 정리하면 사업이나 학업의 기반을 닦습니다."
    },
    {
      "keywords": [
        "서적",
        "책을",
        "문서",
        "독서",
        "책이"
      ],
      "score": 2,
      "category": "물건",
      "description": "지식, 진리, 스승",
      "advice": "깊은 지식을 얻거나 깨달음을 얻게 됩니다."
    },
    {
      "keywords": [
        "만년필",
        "펜을",
        "연필",
        "펜이",
        "볼펜"
      ],
      "score": 1,
      "category": "물건",
      "description": "주도권, 계획, 소식",
      "advice": "자신의 뜻대로 일을 계획하고 추진하게 됩니다."
    },
    {
      "keywords": [
        "비행기",
        "여객기",
        "전투기"
      ],
      "score": 3,
      "category": "물건",
      "description": "상승, 야망, 공공기관",
      "advice": "지위가 급상승하거나 큰 기관의 도움을 받습니다. 비행기를 타면 승진합니다."
    },
    {
      "keywords": [
        "선박",
        "요트",
        "나룻배",
        "타는 배"
      ],
      "score": 1,
      "category": "물건",
      "description": "인생, 가정, 사업체",
      "advice": "배가 순항하면 만사형통이나, 파선을 하면 가정이나 사업에 위기가 닥칩니다."
    },
    {
      "keywords": [
        "자전거",
        "오토바이"
      ],
      "score": 1,
      "category": "물건",
      "description": "노력, 진행, 협동",
      "advice": "꾸준히 노력하여 목표를 향해 나아갑니다. 오토바이는 속도전을 의미합니다."
    },
    {
      "keywords": [
        "사진",
        "앨범",
        "초상화"
      ],
      "score": 1,
      "category": "물건",
      "description": "기억, 소식, 증거",
      "advice": "반가운 소식을 듣거나 과거를 회상할 일이 생깁니다."
    },
    {
      "keywords": [
        "인형",
        "장난감"
      ],
      "score": 0,
      "category": "물건",
      "description": "순수, 고독, 통제",
      "advice": "동심으로 돌아가거나, 반대로 누군가에게 조종당할 수도 있습니다."
    },
    {
      "keywords": [
        "바느질",
        "바늘",
        "실타래",
        "바느질 실",
        "털실"
      ],
      "score": 1,
      "category": "물건",
      "description": "보완, 연결, 해결",
      "advice": "떨어진 것을 잇고 부족한 것을 채워줍니다. 인연을 맺어주기도 합니다."
    },
    {
      "keywords": [
        "가족",
        "식구",
        "친척"
      ],
      "score": 1,
      "category": "인물",
      "description": "협력, 근심, 실제 인물",
      "advice": "가족이 모여 웃으면 길몽, 싸우거나 울면 흉몽입니다."
    },
    {
      "keywords": [
        "남편",
        "아내",
        "배우자"
      ],
      "score": 1,
      "category": "인물",
      "description": "반려자, 애착, 또 다른 자아",
      "advice": "배우자와 사이가 좋으면 가정이 화목하고 일이 잘 풀립니다."
    },
    {
      "keywords": [
        "아들",
        "딸",
        "자녀"
      ],
      "score": 1,
      "category": "인물",
      "description": "애착, 근심, 미래",
      "advice": "자녀가 건강하면 길몽, 아프거나 다치면 근심이 생깁니다."
    },
    {
      "keywords": [
        "형제",
        "자매",
        "남매"
      ],
      "score": 1,
      "category": "인물",
      "description": "경쟁자, 협력자, 분신",
      "advice": "형제와 싸우면 오히려 집안이 화목해지는 경우도 있습니다."
    },
    {
      "keywords": [
        "낯선 사람",
        "모르는 사람"
      ],
      "score": 0,
      "category": "인물",
      "description": "새로운 일, 경계, 또 다른 자아",
      "advice": "낯선 사람이 호의적이면 귀인, 적대적이면 방해꾼일 수 있습니다."
    },
    {
      "keywords": [
        "거지",
        "노숙자"
      ],
      "score": 2,
      "category": "인물",
      "description": "고독, 자유, 역설적 행운",
      "advice": "자신이 거지가 되면 오히려 재물이 들어오는 길몽입니다."
    },
    {
      "keywords": [
        "마녀",
        "마법사"
      ],
      "score": 0,
      "category": "인물",
      "description": "지혜, 유혹, 신비",
      "advice": "지혜로운 조언을 얻거나 유혹에 빠질 수 있습니다."
    },
    {
      "keywords": [
        "천사",
        "선녀"
      ],
      "score": 4,
      "category": "인물",
      "description": "구원, 인도, 행복",
      "advice": "어려움에서 벗어나고 큰 행복을 맛보게 됩니다."
    },
    {
      "keywords": [
        "얼굴",
        "안면"
      ],
      "score": 1,
      "category": "신체",
      "description": "평판, 마음, 상태",
      "advice": "얼굴이 맑으면 운세가 좋고, 어둡거나 다치면 명예가 손상됩니다."
    },
    {
      "keywords": [
        "귀가",
        "귓속"
      ],
      "score": 1,
      "category": "신체",
      "description": "소식, 판단, 통신",
      "advice": "귀가 커지면 좋은 소식을 듣고, 귀가 막히면 답답한 일이 생깁니다."
    },
    {
      "keywords": [
        "코가",
        "콧물"
      ],
      "score": 1,
      "category": "신체",
      "description": "자존심, 재물, 직관",
      "advice": "코가 높으면 자존심이 세지고, 코피가 나면 재물이 들어옵니다."
    },
    {
      "keywords": [
        "입술",
        "혀를",
        "입이",
        "내 혀",
        "혓바닥"
      ],
      "score": 1,
      "category": "신체",
      "description": "가문, 식복, 말",
      "advice": "입이 크면 식복이 좋고, 혀를 다치면 말조심해야 합니다."
    },
    {
      "keywords": [
        "목이",
        "목구멍"
      ],
      "score": 1,
      "category": "신체",
      "description": "생명선, 권위, 소통",
      "advice": "목을 잡히면 굴복당하지만, 목이 굵어지면 권위가 섭니다."
    },
    {
      "keywords": [
        "어깨"
      ],
      "score": 1,
      "category": "신체",
      "description": "책임, 권력, 짐",
      "advice": "어깨가 무거우면 짐이 많고, 어깨를 펴면 당당해집니다."
    },
    {
      "keywords": [
        "등 뒤",
        "등을"
      ],
      "score": 0,
      "category": "신체",
      "description": "배신, 의지, 숨겨진 것",
      "advice": "등을 보이면 패배나 도망을, 등에 업히면 도움을 받습니다."
    },
    {
      "keywords": [
        "가슴",
        "유방"
      ],
      "score": 1,
      "category": "신체",
      "description": "마음, 모성, 포용",
      "advice": "가슴이 답답하면 근심이, 가슴이 넓어지면 도량이 넓어집니다."
    },
    {
      "keywords": [
        "복부",
        "배가 아픈"
      ],
      "score": 1,
      "category": "신체",
      "description": "저장, 욕심, 태동",
      "advice": "배가 부르면 풍요롭고, 배가 아프면 뇌물을 받거나 탈이 날 수 있습니다."
    },
    {
      "keywords": [
        "발을",
        "내 발",
        "발목",
        "다리",
        "무릎",
        "맨발",
        "발이"
      ],
      "score": 1,
      "category": "신체",
      "description": "기반, 이동, 부하직원",
      "advice": "다리가 튼튼하면 아랫사람이 잘 따르고 기반이 굳건합니다."
    },
    {
      "keywords": [
        "피부",
        "살갗"
      ],
      "score": 0,
      "category": "신체",
      "description": "보호, 접촉, 감각",
      "advice": "피부병이 생기면 근심이 생기지만, 피부가 고우면 사랑받습니다."
    },
    {
      "keywords": [
        "뼈",
        "해골"
      ],
      "score": 0,
      "category": "신체",
      "description": "핵심, 진실, 비밀",
      "advice": "뼈만 남으면 실속은 없으나 핵심을 찌르는 통찰을 의미합니다."
    },
    {
      "keywords": [
        "다툼",
        "전투",
        "싸움을",
        "격투"
      ],
      "score": 0,
      "category": "행동",
      "description": "갈등, 경쟁, 해결",
      "advice": "싸워서 이기면 길몽, 지면 흉몽입니다. 피를 보면 재물운입니다."
    },
    {
      "keywords": [
        "살인",
        "죽이는"
      ],
      "score": 3,
      "category": "행동",
      "description": "성취, 정복, 해결",
      "advice": "상대를 죽이면 일을 완벽하게 처리하고 큰 성과를 거둡니다."
    },
    {
      "keywords": [
        "키스",
        "뽀뽀"
      ],
      "score": 2,
      "category": "행동",
      "description": "소식, 계약, 연애",
      "advice": "기분 좋은 키스는 좋은 소식이나 계약 성사를 의미합니다."
    },
    {
      "keywords": [
        "성관계",
        "섹스",
        "동침"
      ],
      "score": 2,
      "category": "행동",
      "description": "계약, 체결, 비밀, 결합",
      "advice": "일거리의 성사나 계약 체결을 상징합니다. 만족스러울수록 결과가 좋습니다."
    },
    {
      "keywords": [
        "청소",
        "정리"
      ],
      "score": 2,
      "category": "행동",
      "description": "해결, 정화, 손님",
      "advice": "복잡한 문제가 해결되고 마음이 상쾌해집니다. 손님을 맞을 준비입니다."
    },
    {
      "keywords": [
        "빨래",
        "세탁"
      ],
      "score": 1,
      "category": "행동",
      "description": "해소, 정화, 변화",
      "advice": "근심 걱정을 씻어내고 새로운 마음으로 시작합니다."
    },
    {
      "keywords": [
        "구토",
        "토하는"
      ],
      "score": -1,
      "category": "행동",
      "description": "반환, 상실, 해소",
      "advice": "먹은 것을 토하면 뇌물을 돌려주거나 이득을 잃지만, 체증이 내려가면 해결입니다."
    },
    {
      "keywords": [
        "노래를",
        "가수"
      ],
      "score": 1,
      "category": "행동",
      "description": "표현, 호소, 선전",
      "advice": "자신의 주장을 널리 알리거나 감정을 표현하게 됩니다."
    },
    {
      "keywords": [
        "무용",
        "춤을"
      ],
      "score": 0,
      "category": "행동",
      "description": "과시, 비난, 격렬함",
      "advice": "신나게 춤을 추면 주도권을 쥐지만, 남이 춤추는 걸 보면 비난받을 수 있습니다."
    },
    {
      "keywords": [
        "절벽",
        "낭떠러지"
      ],
      "score": -2,
      "category": "장소",
      "description": "위기, 한계, 공포",
      "advice": "진퇴양난의 위기에 처할 수 있습니다. 마음을 굳게 먹어야 합니다."
    },
    {
      "keywords": [
        "교량",
        "다리를 건너"
      ],
      "score": 1,
      "category": "장소",
      "description": "연결, 전환점, 수단",
      "advice": "다리를 건너면 난관을 극복하고 새로운 세상으로 나아갑니다."
    },
    {
      "keywords": [
        "시장",
        "마트",
        "백화점"
      ],
      "score": 1,
      "category": "장소",
      "description": "교류, 선택, 욕망",
      "advice": "많은 사람들 속에서 새로운 기회를 찾거나 물건을 고르게 됩니다."
    },
    {
      "keywords": [
        "부엌",
        "주방"
      ],
      "score": 1,
      "category": "장소",
      "description": "준비, 재물, 기반",
      "advice": "부엌에서 요리하면 새로운 일을 시작하거나 재물을 불립니다."
    },
    {
      "keywords": [
        "침실",
        "안방"
      ],
      "score": 1,
      "category": "장소",
      "description": "사생활, 부부, 안식",
      "advice": "가장 편안하고 은밀한 공간으로, 부부 관계나 개인적인 일을 상징합니다."
    },
    {
      "keywords": [
        "나비",
        "나비가"
      ],
      "score": 1,
      "category": "동물",
      "description": "사랑, 허영, 예술",
      "advice": "아름다운 사랑을 하거나 예술적 작품을 발표합니다."
    },
    {
      "keywords": [
        "잠자리",
        "고추잠자리"
      ],
      "score": 0,
      "category": "동물",
      "description": "소식, 불안, 인연",
      "advice": "먼 곳에서 소식이 오거나 새로운 인연을 만납니다."
    },
    {
      "keywords": [
        "귀뚜라미"
      ],
      "score": -1,
      "category": "동물",
      "description": "고독, 가을, 소식",
      "advice": "외로움을 느끼거나 슬픈 소식을 들을 수 있습니다."
    },
    {
      "keywords": [
        "거머리"
      ],
      "score": -1,
      "category": "동물",
      "description": "착취, 손실, 집착",
      "advice": "자신의 이익을 뺏기는 일이 생기거나 귀찮은 사람에게 시달립니다."
    },
    {
      "keywords": [
        "달팽이"
      ],
      "score": -1,
      "category": "동물",
      "description": "느림, 곤란, 답답함",
      "advice": "일의 진행이 더디고 답답할 수 있습니다. 인내심이 필요합니다."
    },
    {
      "keywords": [
        "조개",
        "조가비"
      ],
      "score": 1,
      "category": "동물",
      "description": "재물, 입, 여성",
      "advice": "재물을 얻거나 귀한 자식을 얻을 태몽입니다."
    },
    {
      "keywords": [
        "꽃게",
        "게가",
        "큰 게",
        "게를"
      ],
      "score": 0,
      "category": "동물",
      "description": "방어, 고집, 다툼",
      "advice": "자신의 입장을 고수하다 다툼이 생길 수 있습니다."
    },
    {
      "keywords": [
        "오징어",
        "문어",
        "낙지"
      ],
      "score": -1,
      "category": "동물",
      "description": "골치, 얽힘, 두통",
      "advice": "복잡한 문제에 얽히거나 두통을 앓을 수 있습니다."
    },
    {
      "keywords": [
        "물개",
        "바다표범"
      ],
      "score": 1,
      "category": "동물",
      "description": "힘, 여행, 활동",
      "advice": "왕성한 활동을 하거나 여행을 떠나게 됩니다."
    },
    {
      "keywords": [
        "펭귄"
      ],
      "score": 1,
      "category": "동물",
      "description": "협동, 적응, 귀여움",
      "advice": "단체 생활에 잘 적응하고 인기를 얻습니다."
    },
    {
      "keywords": [
        "백합"
      ],
      "score": 1,
      "category": "식물",
      "description": "순수, 슬픔, 사랑",
      "advice": "순수한 사랑을 하거나 장례식 등 슬픈 일이 생길 수도 있습니다."
    },
    {
      "keywords": [
        "연꽃"
      ],
      "score": 3,
      "category": "식물",
      "description": "진리, 탄생, 정화",
      "advice": "어려움 속에서 피어나는 성공이나 깨달음을 의미합니다."
    },
    {
      "keywords": [
        "카네이션"
      ],
      "score": 2,
      "category": "식물",
      "description": "존경, 사랑, 명예",
      "advice": "존경받는 일이 생기거나 부모님께 효도하게 됩니다."
    },
    {
      "keywords": [
        "해바라기"
      ],
      "score": 2,
      "category": "식물",
      "description": "일편단심, 기다림, 동경",
      "advice": "한 가지 일에 몰두하여 성과를 냅니다."
    },
    {
      "keywords": [
        "옥수수"
      ],
      "score": 1,
      "category": "식물",
      "description": "수확, 치아, 결실",
      "advice": "알찬 결실을 맺거나 건강한 치아를 상징합니다."
    },
    {
      "keywords": [
        "감자"
      ],
      "score": 1,
      "category": "식물",
      "description": "재물, 기반, 소득",
      "advice": "땅속의 보물처럼 숨겨진 재물을 얻습니다."
    },
    {
      "keywords": [
        "호박"
      ],
      "score": 4,
      "category": "식물",
      "description": "호박이 넝쿨째, 횡재",
      "advice": "뜻밖의 횡재를 하거나 일이 술술 풀립니다."
    },
    {
      "keywords": [
        "오이"
      ],
      "score": 0,
      "category": "식물",
      "description": "신선함, 실수, 가벼움",
      "advice": "신선한 아이디어가 떠오르거나 사소한 실수를 할 수 있습니다."
    },
    {
      "keywords": [
        "무를 뽑는",
        "김장무"
      ],
      "score": 1,
      "category": "식물",
      "description": "성공, 튼튼함, 노력",
      "advice": "노력의 결과가 튼튼하게 나타납니다."
    },
    {
      "keywords": [
        "배추"
      ],
      "score": 1,
      "category": "식물",
      "description": "재물, 살림, 준비",
      "advice": "재물이 들어오고 살림이 넉넉해집니다."
    },
    {
      "keywords": [
        "검은콩",
        "콩을"
      ],
      "score": -1,
      "category": "식물",
      "description": "분쟁, 시비, 건강",
      "advice": "집안에 다툼이 생기거나 건강에 유의해야 합니다."
    },
    {
      "keywords": [
        "컴퓨터",
        "노트북"
      ],
      "score": 1,
      "category": "물건",
      "description": "정보, 일, 복잡함",
      "advice": "정보를 수집하거나 복잡한 일을 처리하게 됩니다."
    },
    {
      "keywords": [
        "텔레비전",
        "TV"
      ],
      "score": 0,
      "category": "물건",
      "description": "소식, 관망, 간접경험",
      "advice": "세상 돌아가는 소식을 듣거나 남의 일을 구경하게 됩니다."
    },
    {
      "keywords": [
        "라디오"
      ],
      "score": 0,
      "category": "물건",
      "description": "소문, 뉴스, 말다툼",
      "advice": "주변의 소문에 휘말리거나 누군가와 언쟁을 할 수 있습니다."
    },
    {
      "keywords": [
        "냉장고"
      ],
      "score": 1,
      "category": "물건",
      "description": "보관, 안전, 검사",
      "advice": "자산을 안전하게 보관하거나 자신의 내면을 점검합니다."
    },
    {
      "keywords": [
        "세탁기"
      ],
      "score": 1,
      "category": "물건",
      "description": "수정, 보완, 서두름",
      "advice": "잘못된 것을 바로잡거나 일을 서둘러 처리하게 됩니다."
    },
    {
      "keywords": [
        "선풍기",
        "에어컨"
      ],
      "score": 1,
      "category": "물건",
      "description": "해소, 시원함, 도움",
      "advice": "답답한 상황이 해소되고 시원한 해결책을 찾습니다."
    },
    {
      "keywords": [
        "난로",
        "히터"
      ],
      "score": 2,
      "category": "물건",
      "description": "열정, 자원, 희망",
      "advice": "따뜻한 도움을 받거나 사업에 열정이 생깁니다."
    },
    {
      "keywords": [
        "전등",
        "불빛",
        "조명"
      ],
      "score": 2,
      "category": "물건",
      "description": "희망, 발견, 인도",
      "advice": "어둠 속에서 희망을 발견하고 갈 길을 찾습니다."
    },
    {
      "keywords": [
        "양초",
        "촛불"
      ],
      "score": 2,
      "category": "물건",
      "description": "기원, 희생, 사랑",
      "advice": "소원을 빌거나 누군가를 위해 헌신하게 됩니다."
    },
    {
      "keywords": [
        "커튼",
        "블라인드"
      ],
      "score": 0,
      "category": "물건",
      "description": "비밀, 차단, 경계",
      "advice": "비밀을 간직하거나 외부와의 소통을 차단하게 됩니다."
    },
    {
      "keywords": [
        "카펫",
        "양탄자"
      ],
      "score": 1,
      "category": "물건",
      "description": "지위, 환영, 허세",
      "advice": "귀한 손님을 맞이하거나 자신의 지위를 과시합니다."
    },
    {
      "keywords": [
        "수건",
        "타월"
      ],
      "score": 0,
      "category": "물건",
      "description": "정리, 질병, 피로",
      "advice": "피로를 풀거나 병이 낫습니다. 혹은 일이 정리됩니다."
    },
    {
      "keywords": [
        "비누"
      ],
      "score": 1,
      "category": "물건",
      "description": "반성, 정화, 비밀",
      "advice": "자신의 잘못을 씻어내거나 비밀이 드러날 수 있습니다."
    },
    {
      "keywords": [
        "칫솔",
        "양치"
      ],
      "score": 1,
      "category": "물건",
      "description": "협조, 정화, 언어",
      "advice": "언어 생활을 가다듬거나 협조자의 도움을 받습니다."
    },
    {
      "keywords": [
        "면도기",
        "면도"
      ],
      "score": 1,
      "category": "물건",
      "description": "결단, 정리, 시원함",
      "advice": "어려운 일을 결단력 있게 처리하고 마음이 시원해집니다."
    },
    {
      "keywords": [
        "빗",
        "머리빗"
      ],
      "score": 1,
      "category": "물건",
      "description": "해결, 치료, 정돈",
      "advice": "복잡한 문제가 해결되거나 병이 낫습니다."
    },
    {
      "keywords": [
        "도서관"
      ],
      "score": 1,
      "category": "장소",
      "description": "학문, 연구, 계획",
      "advice": "깊이 있는 연구를 하거나 미래를 계획하게 됩니다."
    },
    {
      "keywords": [
        "박물관"
      ],
      "score": 1,
      "category": "장소",
      "description": "과거, 기록, 영감",
      "advice": "과거를 통해 교훈을 얻거나 새로운 영감을 얻습니다."
    },
    {
      "keywords": [
        "영화관",
        "극장"
      ],
      "score": 0,
      "category": "장소",
      "description": "관찰, 허상, 감상",
      "advice": "남의 일을 구경하거나 잠시 환상에 젖습니다."
    },
    {
      "keywords": [
        "호텔",
        "여관"
      ],
      "score": 0,
      "category": "장소",
      "description": "임시, 여행, 연애",
      "advice": "잠시 머무르는 곳으로, 임시적인 일이나 연애를 상징합니다."
    },
    {
      "keywords": [
        "공항"
      ],
      "score": 0,
      "category": "장소",
      "description": "변화, 대기, 만남",
      "advice": "새로운 세상으로 나아가기 위한 변화의 시점입니다."
    },
    {
      "keywords": [
        "기차역",
        "지하철역"
      ],
      "score": 0,
      "category": "장소",
      "description": "출발, 도착, 과정",
      "advice": "인생의 새로운 단계로 진입하거나 목표를 향해 출발합니다."
    },
    {
      "keywords": [
        "항구",
        "부두"
      ],
      "score": 0,
      "category": "장소",
      "description": "정착, 떠남, 무역",
      "advice": "긴 여정을 마치고 정착하거나 새로운 곳으로 떠납니다."
    },
    {
      "keywords": [
        "공원"
      ],
      "score": 1,
      "category": "장소",
      "description": "휴식, 평화, 자연",
      "advice": "바쁜 일상에서 벗어나 휴식을 취하고 안정을 찾습니다."
    },
    {
      "keywords": [
        "놀이터"
      ],
      "score": 0,
      "category": "장소",
      "description": "동심, 사업, 경쟁",
      "advice": "어린 시절을 회상하거나, 사업장에서 경쟁하게 됩니다."
    },
    {
      "keywords": [
        "정원",
        "화단"
      ],
      "score": 2,
      "category": "장소",
      "description": "가정, 내면, 행복",
      "advice": "가정이 화목하고 내면이 아름답게 가꾸어집니다."
    },
    {
      "keywords": [
        "농장",
        "목장"
      ],
      "score": 2,
      "category": "장소",
      "description": "생산, 부, 노력",
      "advice": "노력한 만큼 풍성한 수확을 거두게 됩니다."
    },
    {
      "keywords": [
        "공장"
      ],
      "score": 1,
      "category": "장소",
      "description": "생산, 분주함, 계획",
      "advice": "일이 많아지고 바쁘게 움직여 성과를 냅니다."
    }
  ],
  "modifiers": [
    {
      "keywords": [
        "쫓기",
        "쫓아",
        "도망",
        "피하",
        "숨는",
        "추격"
      ],
      "score": -3,
      "description": "심리적 압박, 불안",
      "advice": "현재 상황에 대한 불안감이 큽니다. 스트레스 관리가 필요합니다."
    },
    {
      "keywords": [
        "죽이",
        "잡는",
        "이기",
        "물리치",
        "승리",
        "제압"
      ],
      "score": 3,
      "description": "성취, 정복, 해결",
      "advice": "적극적으로 문제를 해결하고 성취를 이룹니다. 자신감을 가지세요."
    },
    {
      "keywords": [
        "물리",
        "물었",
        "물어",
        "공격",
        "다치",
        "아프",
        "피나",
        "상처",
        "깨지",
        "부러지",
        "잘리"
      ],
      "score": -2,
      "description": "피해, 손실, 비판",
      "advice": "뜻밖의 손해나 배신, 혹은 남들의 비판을 받을 수 있습니다."
    },
    {
      "keywords": [
        "웃는",
        "행복",
        "즐거",
        "기쁘",
        "만족",
        "미소"
      ],
      "score": 2,
      "description": "만족, 기쁨, 소원성취",
      "advice": "현재 상황에 만족하고 좋은 결과를 기대할 수 있습니다."
    },
    {
      "keywords": [
        "우는",
        "슬퍼",
        "눈물",
        "통곡",
        "오열"
      ],
      "score": 1,
      "description": "해소, 정화, 기쁨",
      "advice": "억눌린 감정이 해소되고, 꿈과 반대로 기쁜 일이 생길 역설적 징조입니다."
    },
    {
      "keywords": [
        "잃어버리",
        "없어지",
        "떨어뜨리",
        "도난",
        "빠지",
        "분실"
      ],
      "score": -2,
      "description": "상실, 불안, 곤란",
      "advice": "소중한 것을 잃거나 기회를 놓칠 수 있으니 주의하세요."
    },
    {
      "keywords": [
        "받는",
        "줍는",
        "얻는",
        "생기",
        "선물",
        "취득"
      ],
      "score": 2,
      "description": "획득, 행운, 권리",
      "advice": "뜻밖의 이득이나 권리를 얻게 됩니다. 태몽일 수도 있습니다."
    },
    {
      "keywords": [
        "싸우",
        "다투",
        "욕하",
        "언쟁",
        "시비"
      ],
      "score": -1,
      "description": "갈등, 경쟁, 불만",
      "advice": "주변 사람과의 마찰이 생길 수 있으나, 싸움에서 이기면 길몽입니다."
    },
    {
      "keywords": [
        "무서",
        "공포",
        "두려",
        "떨는",
        "놀라",
        "무섭"
      ],
      "score": -2,
      "description": "불안, 경고, 위축",
      "advice": "자신감이 부족하거나 건강에 유의해야 합니다. 마음을 편안히 가지세요."
    },
    {
      "keywords": [
        "크고",
        "거대",
        "많은",
        "풍성",
        "가득",
        "넘치"
      ],
      "score": 1,
      "description": "확장, 풍요, 세력",
      "advice": "규모가 커질수록 운세의 강도도 강해집니다. 좋은 상징이라면 더욱 좋습니다."
    },
    {
      "keywords": [
        "작은",
        "초라",
        "부서진",
        "낡은",
        "시든"
      ],
      "score": -1,
      "description": "축소, 쇠락, 미흡",
      "advice": "결과가 기대에 미치지 못하거나 쇠퇴할 징조입니다."
    },
    {
      "keywords": [
        "타는",
        "운전",
        "조종",
        "탑승"
      ],
      "score": 1,
      "description": "주도, 진행, 책임",
      "advice": "어떤 일을 주도적으로 이끌어가거나 책임을 맡게 됩니다."
    },
    {
      "keywords": [
        "관찰",
        "구경",
        "바라보",
        "주시",
        "목격"
      ],
      "score": 0,
      "description": "관망, 탐색, 인식",
      "advice": "어떤 일을 주시하거나 관심을 갖게 됩니다. 대상의 상태가 중요합니다."
    },
    {
      "keywords": [
        "안는",
        "포옹",
        "업는",
        "감싸"
      ],
      "score": 1,
      "description": "보호, 책임, 협력",
      "advice": "누군가를 보호하거나 책임을 떠안게 됩니다. 혹은 협력자를 얻습니다."
    },
    {
      "keywords": [
        "맞는",
        "폭행",
        "구타"
      ],
      "score": 1,
      "description": "비평, 칭찬, 충격",
      "advice": "남에게 맞으면 칭찬을 듣거나, 반대로 비판을 받을 수도 있습니다. 상황에 따라 다릅니다."
    },
    {
      "keywords": [
        "빨간",
        "붉은",
        "홍색",
        "레드"
      ],
      "score": 1,
      "description": "열정, 위험, 경고, 생명",
      "advice": "강렬한 에너지를 의미합니다. 상황에 따라 열정일 수도, 경고일 수도 있습니다."
    },
    {
      "keywords": [
        "하얀",
        "흰",
        "백색",
        "화이트"
      ],
      "score": 1,
      "description": "순수, 평화, 죽음, 새로운 시작",
      "advice": "순수한 시작이나 평화를 상징하지만, 때로는 상복(죽음)을 의미하기도 합니다."
    },
    {
      "keywords": [
        "검은",
        "까만",
        "흑색",
        "어두운",
        "블랙"
      ],
      "score": -2,
      "description": "불안, 비밀, 죽음, 권위",
      "advice": "일반적으로 좋지 않은 징조나 비밀스러운 일을 암시합니다."
    },
    {
      "keywords": [
        "파란",
        "푸른",
        "청색",
        "블루"
      ],
      "score": 1,
      "description": "젊음, 냉정, 희망, 신선함",
      "advice": "신선하고 희망찬 기운을 의미합니다."
    },
    {
      "keywords": [
        "노란",
        "황금색",
        "누런",
        "옐로우"
      ],
      "score": 3,
      "description": "부, 명예, 존귀, 성숙",
      "advice": "재물과 명예를 상징하는 가장 좋은 색상입니다."
    },
    {
      "keywords": [
        "더러운",
        "지저분한",
        "오물"
      ],
      "score": -1,
      "description": "불쾌, 질병, 근심, 수치",
      "advice": "기분이 불쾌했다면 질병이나 근심거리가 생길 수 있습니다. (똥은 예외)"
    },
    {
      "keywords": [
        "깨끗한",
        "맑은",
        "청결한",
        "빛나는"
      ],
      "score": 2,
      "description": "정화, 순조로움, 명예, 건강",
      "advice": "모든 일이 순조롭게 풀리고 건강이 좋아집니다."
    }
  ]
}